{"cameraMode":{"drawMode":0,"name":"Shaded","section":"Shading Mode"},"sceneLighting":true,"audioPlay":false,"sceneViewState":{"m_AlwaysRefresh":false,"showFog":true,"showSkybox":true,"showFlares":true,"showImageEffects":true,"showParticleSystems":true,"showVisualEffectGraphs":true,"m_FxEnabled":true},"in2DMode":false,"pivot":{"x":0.34695038199424746,"y":6.138329029083252,"z":-13.820033073425293},"rotation":{"x":-0.15494541823863984,"y":0.05440209060907364,"z":-0.00854470394551754,"w":-0.9863934516906738},"size":0.8660253882408142,"orthographic":false}